input_output_build
