Metadata-Version: 2.4
Name: input-output-build
Version: 0.1.1
Summary: Utilities for building and testing input/output pipelines.
Author-email: John Malcolm Vich <vich.malcolm.john@bollywood.com>
Maintainer-email: John Malcolm Vich <vich.malcolm.john@bollywood.com>
Keywords: input,output,build,pipeline,automation
Classifier: Development Status :: 3 - Alpha
Classifier: Intended Audience :: Developers
Classifier: License :: OSI Approved :: MIT License
Classifier: Programming Language :: Python
Classifier: Programming Language :: Python :: 3
Classifier: Programming Language :: Python :: 3.9
Classifier: Programming Language :: Python :: 3.10
Classifier: Programming Language :: Python :: 3.11
Classifier: Programming Language :: Python :: 3.12
Classifier: Operating System :: OS Independent
Classifier: Topic :: Software Development :: Build Tools
Requires-Python: >=3.9
